[
  {
    "content_without_front_matter": "# Регламент подачи и обработки внутренних заявок на закупку\n\n**Компания:** ООО «Вектор Дистрибуция»  \n**Версия:** 1.0  \n**Дата вступления в силу:** 01.08.2026\n\n## 1. Назначение\n\nРегламент устанавливает единый порядок подачи, проверки, регистрации и обработки нерегулярных закупок товаров и услуг.\n\nЦели:\n\n- исключить потерю заявок;\n- обеспечить полноту требований;\n- сократить время уточнений;\n- сделать сроки и статусы прозрачными;\n- повысить управляемость затрат.\n\nРегламент не применяется к закупкам основного товарного ассортимента и регулярным заказам по утверждённому графику.\n\n## 2. Участники\n\n**Внутренний заказчик** формулирует потребность, характеристики, количество, сроки, бюджет и критерии приёмки.\n\n**Отдел закупок** проверяет полноту заявки, определяет способ закупки, организует работу с поставщиками и обновляет статус.\n\n**Руководитель подразделения** подтверждает потребность, внебюджетные расходы и срочность.\n\n**Финансовый отдел** проверяет статью бюджета и наличие финансирования.\n\n## 3. Канал подачи\n\nОфициальной считается только заявка, которая:\n\n1. заполнена через ассистента;\n2. проверена инициатором;\n3. явно подтверждена;\n4. получила уникальный номер;\n5. имеет статус `Передана в отдел закупок`.\n\nУстные просьбы, письма и сообщения в мессенджере не заменяют регистрацию.\n\n## 4. Общие обязательные сведения\n\n- краткое название;\n- тип: товар или услуга;\n- категория;\n- инициатор и подразделение;\n- обоснование;\n- описание предмета;\n- количество или объём;\n- требуемая дата;\n- место поставки или оказания услуги;\n- ориентировочный общий бюджет;\n- бюджетный статус;\n- контактное лицо;\n- обязательные поля по категории.\n\n## 5. Требования к товару\n\nУказываются:\n\n- наименование и назначение;\n- количество и единица измерения;\n- технические, функциональные и качественные характеристики;\n- требования к совместимости;\n- комплектность, упаковка, гарантия;\n- место и срок поставки;\n- допустимость эквивалента.\n\nСсылка на интернет-магазин может быть референсом, но не заменяет характеристик.\n\nЕсли указан бренд, применяется формулировка «или эквивалент», кроме обоснованных случаев совместимости, запасных частей или корпоративного стандарта.\n\n## 6. Требования к услуге\n\nУказываются:\n\n- ожидаемый результат;\n- состав и объём работ;\n- сроки и место;\n- требования к исполнителю;\n- формат результата;\n- критерии приёмки;\n- требования к отчётности;\n- ограничения и зависимости.\n\nФормулировки «качественно», «красиво», «срочно» без измеримых требований недостаточны.\n\n## 7. Работа ассистента\n\nАссистент:\n\n- определяет тип и предполагаемую категорию;\n- извлекает сведения из свободного текста;\n- сравнивает заявку с матрицей обязательных полей;\n- задаёт вопросы по отсутствующим данным;\n- выявляет формальные ошибки;\n- показывает итоговую карточку.\n\nАссистент не выбирает поставщика, не одобряет бюджет и не оценивает целесообразность закупки.\n\n## 8. Регистрация и проверка\n\nПосле подтверждения заявке присваивается номер вида `PR-ГГГГ-XXXX`.\n\nПервичная проверка отделом закупок проводится в течение одного рабочего дня. Возможные результаты:\n\n- `Принята в работу`;\n- `Требует доработки`;\n- `На согласовании`;\n- `Отклонена`.\n\nПри возврате закупщик обязан указать конкретные недостающие сведения. Номер и история заявки сохраняются.\n\n## 9. Срочная заявка\n\nДля срочной заявки обязательны:\n\n- причина срочности;\n- дата возникновения потребности;\n- последствия задержки;\n- крайняя допустимая дата;\n- подтверждение руководителя;\n- возможный временный вариант.\n\nСрочность не гарантирует исполнение в желаемый срок.\n\n## 10. Бюджет\n\nУказывается общая ориентировочная стоимость всей заявки.\n\nДля бюджетной закупки указываются статья и центр финансовой ответственности.\n\nВнебюджетная закупка требует дополнительного согласования.\n\n## 11. Единственный поставщик\n\nЕсли заказчик исключает альтернативы, он предоставляет основание: исключительные права, техническая совместимость, продолжение работ, отсутствие равноценной замены или подтверждённая чрезвычайная ситуация.\n\nПредпочтение конкретному поставщику без обоснования не является основанием.\n\n## 12. Отмена и статусы\n\nИнициатор может отменить заявку до статуса `Принята в работу`. После начала закупки отмена согласуется с закупщиком.\n\nЗакупщик обновляет статус после проверки, согласования, выбора поставщика, изменения срока и завершения закупки.\n\n## 13. Ответственность\n\nИнициатор отвечает за предметные и технические требования.\n\nОтдел закупок отвечает за соблюдение закупочного процесса.\n\nАссистент проверяет полноту и формальную непротиворечивость, но не подтверждает техническую правильность требований.\n",
    "document_id": "kb-001",
    "document_type": "regulation",
    "effective_date": "2026-08-01",
    "filename": "01_Регламент_подачи_и_обработки_заявок.md",
    "language": "ru",
    "owner": "Отдел закупок",
    "priority": 1,
    "raw_content": "---\ndocument_id: kb-001\ntitle: Регламент подачи и обработки заявок\ndocument_type: regulation\nversion: \"1.0\"\neffective_date: \"2026-08-01\"\nowner: Отдел закупок\npriority: 1\nstatus: active\nlanguage: ru\n---\n\n# Регламент подачи и обработки внутренних заявок на закупку\n\n**Компания:** ООО «Вектор Дистрибуция»  \n**Версия:** 1.0  \n**Дата вступления в силу:** 01.08.2026\n\n## 1. Назначение\n\nРегламент устанавливает единый порядок подачи, проверки, регистрации и обработки нерегулярных закупок товаров и услуг.\n\nЦели:\n\n- исключить потерю заявок;\n- обеспечить полноту требований;\n- сократить время уточнений;\n- сделать сроки и статусы прозрачными;\n- повысить управляемость затрат.\n\nРегламент не применяется к закупкам основного товарного ассортимента и регулярным заказам по утверждённому графику.\n\n## 2. Участники\n\n**Внутренний заказчик** формулирует потребность, характеристики, количество, сроки, бюджет и критерии приёмки.\n\n**Отдел закупок** проверяет полноту заявки, определяет способ закупки, организует работу с поставщиками и обновляет статус.\n\n**Руководитель подразделения** подтверждает потребность, внебюджетные расходы и срочность.\n\n**Финансовый отдел** проверяет статью бюджета и наличие финансирования.\n\n## 3. Канал подачи\n\nОфициальной считается только заявка, которая:\n\n1. заполнена через ассистента;\n2. проверена инициатором;\n3. явно подтверждена;\n4. получила уникальный номер;\n5. имеет статус `Передана в отдел закупок`.\n\nУстные просьбы, письма и сообщения в мессенджере не заменяют регистрацию.\n\n## 4. Общие обязательные сведения\n\n- краткое название;\n- тип: товар или услуга;\n- категория;\n- инициатор и подразделение;\n- обоснование;\n- описание предмета;\n- количество или объём;\n- требуемая дата;\n- место поставки или оказания услуги;\n- ориентировочный общий бюджет;\n- бюджетный статус;\n- контактное лицо;\n- обязательные поля по категории.\n\n## 5. Требования к товару\n\nУказываются:\n\n- наименование и назначение;\n- количество и единица измерения;\n- технические, функциональные и качественные характеристики;\n- требования к совместимости;\n- комплектность, упаковка, гарантия;\n- место и срок поставки;\n- допустимость эквивалента.\n\nСсылка на интернет-магазин может быть референсом, но не заменяет характеристик.\n\nЕсли указан бренд, применяется формулировка «или эквивалент», кроме обоснованных случаев совместимости, запасных частей или корпоративного стандарта.\n\n## 6. Требования к услуге\n\nУказываются:\n\n- ожидаемый результат;\n- состав и объём работ;\n- сроки и место;\n- требования к исполнителю;\n- формат результата;\n- критерии приёмки;\n- требования к отчётности;\n- ограничения и зависимости.\n\nФормулировки «качественно», «красиво», «срочно» без измеримых требований недостаточны.\n\n## 7. Работа ассистента\n\nАссистент:\n\n- определяет тип и предполагаемую категорию;\n- извлекает сведения из свободного текста;\n- сравнивает заявку с матрицей обязательных полей;\n- задаёт вопросы по отсутствующим данным;\n- выявляет формальные ошибки;\n- показывает итоговую карточку.\n\nАссистент не выбирает поставщика, не одобряет бюджет и не оценивает целесообразность закупки.\n\n## 8. Регистрация и проверка\n\nПосле подтверждения заявке присваивается номер вида `PR-ГГГГ-XXXX`.\n\nПервичная проверка отделом закупок проводится в течение одного рабочего дня. Возможные результаты:\n\n- `Принята в работу`;\n- `Требует доработки`;\n- `На согласовании`;\n- `Отклонена`.\n\nПри возврате закупщик обязан указать конкретные недостающие сведения. Номер и история заявки сохраняются.\n\n## 9. Срочная заявка\n\nДля срочной заявки обязательны:\n\n- причина срочности;\n- дата возникновения потребности;\n- последствия задержки;\n- крайняя допустимая дата;\n- подтверждение руководителя;\n- возможный временный вариант.\n\nСрочность не гарантирует исполнение в желаемый срок.\n\n## 10. Бюджет\n\nУказывается общая ориентировочная стоимость всей заявки.\n\nДля бюджетной закупки указываются статья и центр финансовой ответственности.\n\nВнебюджетная закупка требует дополнительного согласования.\n\n## 11. Единственный поставщик\n\nЕсли заказчик исключает альтернативы, он предоставляет основание: исключительные права, техническая совместимость, продолжение работ, отсутствие равноценной замены или подтверждённая чрезвычайная ситуация.\n\nПредпочтение конкретному поставщику без обоснования не является основанием.\n\n## 12. Отмена и статусы\n\nИнициатор может отменить заявку до статуса `Принята в работу`. После начала закупки отмена согласуется с закупщиком.\n\nЗакупщик обновляет статус после проверки, согласования, выбора поставщика, изменения срока и завершения закупки.\n\n## 13. Ответственность\n\nИнициатор отвечает за предметные и технические требования.\n\nОтдел закупок отвечает за соблюдение закупочного процесса.\n\nАссистент проверяет полноту и формальную непротиворечивость, но не подтверждает техническую правильность требований.\n",
    "sha256": "d8f7176f9721f10243e0f7f0b2dc1c4920d531615c3da46157fa1f97951d8733",
    "status": "active",
    "title": "Регламент подачи и обработки заявок",
    "version": "1.0"
  },
  {
    "content_without_front_matter": "# Шаблон заявки на закупку товара\n\n| Поле | Требование | Пример |\n|---|---|---|\n| Краткое название | 5–7 слов | Ноутбуки для отдела продаж |\n| Категория | По классификатору | IT-оборудование |\n| Инициатор | ФИО и контакт | Анна Петрова |\n| Подразделение | Подразделение-заказчик | Продажи |\n| Обоснование | Зачем нужен товар | Оснащение новых сотрудников |\n| Наименование | Что требуется | Ноутбук |\n| Количество | Число больше нуля | 5 |\n| Единица измерения | шт., комплект и т. п. | шт. |\n| Характеристики | Измеримые требования | RAM от 16 ГБ |\n| Требуемая дата | Дата получения | 15.09.2026 |\n| Место поставки | Адрес или площадка | Центральный офис |\n| Бюджет | Общая сумма | 500 000 руб. |\n| Бюджетный статус | Бюджетная / внебюджетная | Бюджетная |\n| Эквивалент | Да / нет с обоснованием | Да |\n| Контакт | По предметным вопросам | Анна Петрова |\n\n## Дополнительные поля\n\n- бренд или референс;\n- совместимость;\n- упаковка и комплектность;\n- гарантия;\n- сертификаты;\n- график поставки;\n- спецификация;\n- фото или чертёж.\n\n## Правила\n\n1. Несколько позиций объединяются, только если относятся к одной категории.\n2. Указывается общая сумма заявки.\n3. Ссылка не заменяет характеристики.\n4. «Как в прошлый раз» допустимо только со ссылкой на прежнюю заявку.\n5. Дата не может быть в прошлом.\n6. Количество должно быть больше нуля.\n",
    "document_id": "kb-002",
    "document_type": "template",
    "effective_date": "2026-07-21",
    "filename": "02_Шаблон_заявки_на_товар.md",
    "language": "ru",
    "owner": "Отдел закупок",
    "priority": 9,
    "raw_content": "---\ndocument_id: kb-002\ntitle: Шаблон заявки на закупку товара\ndocument_type: template\nversion: \"1.0\"\neffective_date: \"2026-07-21\"\nowner: Отдел закупок\npriority: 9\nstatus: active\nlanguage: ru\n---\n\n# Шаблон заявки на закупку товара\n\n| Поле | Требование | Пример |\n|---|---|---|\n| Краткое название | 5–7 слов | Ноутбуки для отдела продаж |\n| Категория | По классификатору | IT-оборудование |\n| Инициатор | ФИО и контакт | Анна Петрова |\n| Подразделение | Подразделение-заказчик | Продажи |\n| Обоснование | Зачем нужен товар | Оснащение новых сотрудников |\n| Наименование | Что требуется | Ноутбук |\n| Количество | Число больше нуля | 5 |\n| Единица измерения | шт., комплект и т. п. | шт. |\n| Характеристики | Измеримые требования | RAM от 16 ГБ |\n| Требуемая дата | Дата получения | 15.09.2026 |\n| Место поставки | Адрес или площадка | Центральный офис |\n| Бюджет | Общая сумма | 500 000 руб. |\n| Бюджетный статус | Бюджетная / внебюджетная | Бюджетная |\n| Эквивалент | Да / нет с обоснованием | Да |\n| Контакт | По предметным вопросам | Анна Петрова |\n\n## Дополнительные поля\n\n- бренд или референс;\n- совместимость;\n- упаковка и комплектность;\n- гарантия;\n- сертификаты;\n- график поставки;\n- спецификация;\n- фото или чертёж.\n\n## Правила\n\n1. Несколько позиций объединяются, только если относятся к одной категории.\n2. Указывается общая сумма заявки.\n3. Ссылка не заменяет характеристики.\n4. «Как в прошлый раз» допустимо только со ссылкой на прежнюю заявку.\n5. Дата не может быть в прошлом.\n6. Количество должно быть больше нуля.\n",
    "sha256": "8fc5a3bfcf7ec4bd9e279beec2825e9ab90abf08acf38cdc0b587bd596b5036f",
    "status": "active",
    "title": "Шаблон заявки на закупку товара",
    "version": "1.0"
  },
  {
    "content_without_front_matter": "# Шаблон заявки на закупку услуги\n\n| Поле | Требование | Пример |\n|---|---|---|\n| Краткое название | Наименование услуги | Дизайн выставочного стенда |\n| Категория | По классификатору | Дизайн и контент |\n| Инициатор | ФИО и контакт | Ольга Соколова |\n| Подразделение | Заказчик | Маркетинг |\n| Обоснование | Бизнес-цель | Участие в выставке |\n| Ожидаемый результат | Что должно быть получено | Макеты и файлы в печать |\n| Состав работ | Основные этапы | 3 концепции и адаптация |\n| Объём | Количество объектов / часов | 6 носителей |\n| Период | Начало и окончание | 10.08–05.09.2026 |\n| Место | Офис / склад / удалённо | Удалённо |\n| Критерии приёмки | Проверяемые условия | Соответствие брендбуку |\n| Исполнитель | Опыт, лицензии, команда | Опыт B2B от 3 лет |\n| Бюджет | Общая сумма | 200 000 руб. |\n| Бюджетный статус | Бюджетная / внебюджетная | Бюджетная |\n| Контакт | По предметным вопросам | Ольга Соколова |\n\n## Дополнительные поля\n\n- этапность;\n- формат отчётности;\n- конфиденциальность;\n- необходимость выезда;\n- права на результат;\n- SLA и сервисные показатели;\n- исходные материалы.\n\n## Правила\n\n1. Результат должен быть проверяемым.\n2. Критерии приёмки не должны быть только субъективными.\n3. Указываются зависимости от исходных данных заказчика.\n4. Для работ на территории компании указываются режим доступа и безопасность.\n5. Для услуг с интеллектуальными правами условия передачи прав описываются отдельно.\n",
    "document_id": "kb-003",
    "document_type": "template",
    "effective_date": "2026-07-21",
    "filename": "03_Шаблон_заявки_на_услугу.md",
    "language": "ru",
    "owner": "Отдел закупок",
    "priority": 9,
    "raw_content": "---\ndocument_id: kb-003\ntitle: Шаблон заявки на закупку услуги\ndocument_type: template\nversion: \"1.0\"\neffective_date: \"2026-07-21\"\nowner: Отдел закупок\npriority: 9\nstatus: active\nlanguage: ru\n---\n\n# Шаблон заявки на закупку услуги\n\n| Поле | Требование | Пример |\n|---|---|---|\n| Краткое название | Наименование услуги | Дизайн выставочного стенда |\n| Категория | По классификатору | Дизайн и контент |\n| Инициатор | ФИО и контакт | Ольга Соколова |\n| Подразделение | Заказчик | Маркетинг |\n| Обоснование | Бизнес-цель | Участие в выставке |\n| Ожидаемый результат | Что должно быть получено | Макеты и файлы в печать |\n| Состав работ | Основные этапы | 3 концепции и адаптация |\n| Объём | Количество объектов / часов | 6 носителей |\n| Период | Начало и окончание | 10.08–05.09.2026 |\n| Место | Офис / склад / удалённо | Удалённо |\n| Критерии приёмки | Проверяемые условия | Соответствие брендбуку |\n| Исполнитель | Опыт, лицензии, команда | Опыт B2B от 3 лет |\n| Бюджет | Общая сумма | 200 000 руб. |\n| Бюджетный статус | Бюджетная / внебюджетная | Бюджетная |\n| Контакт | По предметным вопросам | Ольга Соколова |\n\n## Дополнительные поля\n\n- этапность;\n- формат отчётности;\n- конфиденциальность;\n- необходимость выезда;\n- права на результат;\n- SLA и сервисные показатели;\n- исходные материалы.\n\n## Правила\n\n1. Результат должен быть проверяемым.\n2. Критерии приёмки не должны быть только субъективными.\n3. Указываются зависимости от исходных данных заказчика.\n4. Для работ на территории компании указываются режим доступа и безопасность.\n5. Для услуг с интеллектуальными правами условия передачи прав описываются отдельно.\n",
    "sha256": "f19765009be846610f3bdde411d1be544e2aa3e96185abb32662ac4c013aa1af",
    "status": "active",
    "title": "Шаблон заявки на закупку услуги",
    "version": "1.0"
  },
  {
    "content_without_front_matter": "# Классификатор категорий закупок\n\n| Код | Категория | Тип | Примеры |\n|---|---|---|---|\n| G01 | Офисные принадлежности | Товар | бумага, ручки |\n| G02 | Мебель и оснащение | Товар | столы, кресла |\n| G03 | IT-оборудование | Товар | ноутбуки, мониторы |\n| G04 | IT-периферия | Товар | мыши, гарнитуры |\n| G05 | ПО и лицензии | Товар/услуга | SaaS, лицензии |\n| G06 | Складское оборудование | Товар | стеллажи, тележки |\n| G07 | Погрузочная техника и запчасти | Товар | погрузчики, батареи |\n| G08 | Спецодежда и СИЗ | Товар | обувь, перчатки |\n| G09 | Хозяйственные товары | Товар | инвентарь |\n| G10 | Упаковочные материалы | Товар | коробки, плёнка |\n| G11 | Полиграфическая продукция | Товар | буклеты, каталоги |\n| G12 | Рекламные и POS-материалы | Товар | стенды, баннеры |\n| G13 | Сувенирная продукция | Товар | мерч, подарки |\n| G14 | Электротехнические материалы | Товар | кабели, лампы |\n| G15 | Инженерные запчасти | Товар | фильтры, детали |\n| S01 | Ремонт и обслуживание | Услуга | ремонт оборудования |\n| S02 | Клининговые услуги | Услуга | уборка |\n| S03 | Транспортные услуги | Услуга | доставка, перевозка |\n| S04 | Складские услуги | Услуга | хранение |\n| S05 | IT-разработка и поддержка | Услуга | интеграции |\n| S06 | Маркетинговые услуги | Услуга | исследования, реклама |\n| S07 | Дизайн и контент | Услуга | дизайн, фото, видео |\n| S08 | Организация мероприятий | Услуга | выставки |\n| S09 | Обучение | Услуга | тренинги |\n| S10 | Подбор персонала | Услуга | рекрутинг |\n| S11 | Консалтинг и юридические услуги | Услуга | аудит, консультации |\n| S12 | Переводческие услуги | Услуга | переводы |\n| S13 | Полиграфические услуги | Услуга | печать |\n| S14 | Аренда | Услуга | помещения, техника |\n| S15 | Прочие профессиональные услуги | Услуга | редкие услуги |\n\n## Правила классификации\n\n- Категория определяется по основному результату.\n- Лицензия на ПО — G05, разработка ПО — S05.\n- Печать по готовому макету — S13, закупка готовой полиграфии — G11.\n- При сомнении ассистент предлагает до трёх вариантов.\n- S15 используется только после исключения более точных категорий.\n",
    "document_id": "kb-004",
    "document_type": "classifier",
    "effective_date": "2026-07-21",
    "filename": "04_Классификатор_категорий_закупок.md",
    "language": "ru",
    "owner": "Отдел закупок",
    "priority": 3,
    "raw_content": "---\ndocument_id: kb-004\ntitle: Классификатор категорий закупок\ndocument_type: classifier\nversion: \"1.0\"\neffective_date: \"2026-07-21\"\nowner: Отдел закупок\npriority: 3\nstatus: active\nlanguage: ru\n---\n\n# Классификатор категорий закупок\n\n| Код | Категория | Тип | Примеры |\n|---|---|---|---|\n| G01 | Офисные принадлежности | Товар | бумага, ручки |\n| G02 | Мебель и оснащение | Товар | столы, кресла |\n| G03 | IT-оборудование | Товар | ноутбуки, мониторы |\n| G04 | IT-периферия | Товар | мыши, гарнитуры |\n| G05 | ПО и лицензии | Товар/услуга | SaaS, лицензии |\n| G06 | Складское оборудование | Товар | стеллажи, тележки |\n| G07 | Погрузочная техника и запчасти | Товар | погрузчики, батареи |\n| G08 | Спецодежда и СИЗ | Товар | обувь, перчатки |\n| G09 | Хозяйственные товары | Товар | инвентарь |\n| G10 | Упаковочные материалы | Товар | коробки, плёнка |\n| G11 | Полиграфическая продукция | Товар | буклеты, каталоги |\n| G12 | Рекламные и POS-материалы | Товар | стенды, баннеры |\n| G13 | Сувенирная продукция | Товар | мерч, подарки |\n| G14 | Электротехнические материалы | Товар | кабели, лампы |\n| G15 | Инженерные запчасти | Товар | фильтры, детали |\n| S01 | Ремонт и обслуживание | Услуга | ремонт оборудования |\n| S02 | Клининговые услуги | Услуга | уборка |\n| S03 | Транспортные услуги | Услуга | доставка, перевозка |\n| S04 | Складские услуги | Услуга | хранение |\n| S05 | IT-разработка и поддержка | Услуга | интеграции |\n| S06 | Маркетинговые услуги | Услуга | исследования, реклама |\n| S07 | Дизайн и контент | Услуга | дизайн, фото, видео |\n| S08 | Организация мероприятий | Услуга | выставки |\n| S09 | Обучение | Услуга | тренинги |\n| S10 | Подбор персонала | Услуга | рекрутинг |\n| S11 | Консалтинг и юридические услуги | Услуга | аудит, консультации |\n| S12 | Переводческие услуги | Услуга | переводы |\n| S13 | Полиграфические услуги | Услуга | печать |\n| S14 | Аренда | Услуга | помещения, техника |\n| S15 | Прочие профессиональные услуги | Услуга | редкие услуги |\n\n## Правила классификации\n\n- Категория определяется по основному результату.\n- Лицензия на ПО — G05, разработка ПО — S05.\n- Печать по готовому макету — S13, закупка готовой полиграфии — G11.\n- При сомнении ассистент предлагает до трёх вариантов.\n- S15 используется только после исключения более точных категорий.\n",
    "sha256": "1becbcf59c7efc14e253ba066c9fc1482ba09fe0d37d2ab2bddf3a958dbb0ecd",
    "status": "active",
    "title": "Классификатор категорий закупок",
    "version": "1.0"
  },
  {
    "content_without_front_matter": "# Матрица обязательных полей\n\n## Общие поля\n\nДля всех заявок обязательны: название, тип, категория, инициатор, подразделение, обоснование, требуемая дата, бюджет, бюджетный статус и контактное лицо.\n\n## Категориальные поля\n\n| Категория | Дополнительные обязательные поля |\n|---|---|\n| G02 Мебель | размеры, материал, цвет, количество, место установки |\n| G03 IT-оборудование | характеристики, совместимость, количество, гарантия |\n| G05 ПО | продукт, пользователи, срок лицензии, модель оплаты, требования ИБ |\n| G06 Складское оборудование | нагрузка, габариты, место эксплуатации |\n| G07 Погрузочная техника | тип, грузоподъёмность, высота, режим эксплуатации |\n| G08 Спецодежда | размеры, сезонность, класс защиты, количество |\n| G10 Упаковка | размеры, материал, плотность, печать, количество |\n| G11 Полиграфия | формат, тираж, бумага, цветность, макет |\n| G12 POS-материалы | размеры, материал, конструкция, тираж |\n| G15 Запчасти | модель оборудования, артикул/чертёж, совместимость |\n| S01 Ремонт | объект, неисправность, место, критерии завершения |\n| S03 Транспорт | маршрут, груз, вес/объём, даты, погрузка |\n| S04 Складские услуги | товар, объём, период, операции, условия хранения |\n| S05 IT-разработка | бизнес-требования, интеграции, результат, приёмка |\n| S06 Маркетинг | цель, аудитория, каналы, география, KPI |\n| S07 Дизайн | материалы, форматы, брендбук, сроки, права |\n| S08 Мероприятия | дата, место, участники, программа, состав услуг |\n| S09 Обучение | тема, аудитория, участники, формат, результат |\n| S11 Консалтинг | проблема, результат, объём, формат отчёта |\n| S13 Полиграфия | макет, формат, тираж, материалы, цветность |\n| S14 Аренда | объект, период, место, характеристики, услуги |\n\n## Формальные проверки\n\n- дата не в прошлом;\n- количество больше нуля;\n- сумма неотрицательная;\n- единица измерения указана;\n- окончание не раньше начала;\n- сумма заявки согласована с позициями;\n- при запрете эквивалента есть обоснование;\n- при срочности есть причина;\n- при внебюджетной закупке указан статус согласования.\n",
    "document_id": "kb-005",
    "document_type": "field_matrix",
    "effective_date": "2026-07-21",
    "filename": "05_Матрица_обязательных_полей.md",
    "language": "ru",
    "owner": "Отдел закупок",
    "priority": 2,
    "raw_content": "---\ndocument_id: kb-005\ntitle: Матрица обязательных полей\ndocument_type: field_matrix\nversion: \"1.0\"\neffective_date: \"2026-07-21\"\nowner: Отдел закупок\npriority: 2\nstatus: active\nlanguage: ru\n---\n\n# Матрица обязательных полей\n\n## Общие поля\n\nДля всех заявок обязательны: название, тип, категория, инициатор, подразделение, обоснование, требуемая дата, бюджет, бюджетный статус и контактное лицо.\n\n## Категориальные поля\n\n| Категория | Дополнительные обязательные поля |\n|---|---|\n| G02 Мебель | размеры, материал, цвет, количество, место установки |\n| G03 IT-оборудование | характеристики, совместимость, количество, гарантия |\n| G05 ПО | продукт, пользователи, срок лицензии, модель оплаты, требования ИБ |\n| G06 Складское оборудование | нагрузка, габариты, место эксплуатации |\n| G07 Погрузочная техника | тип, грузоподъёмность, высота, режим эксплуатации |\n| G08 Спецодежда | размеры, сезонность, класс защиты, количество |\n| G10 Упаковка | размеры, материал, плотность, печать, количество |\n| G11 Полиграфия | формат, тираж, бумага, цветность, макет |\n| G12 POS-материалы | размеры, материал, конструкция, тираж |\n| G15 Запчасти | модель оборудования, артикул/чертёж, совместимость |\n| S01 Ремонт | объект, неисправность, место, критерии завершения |\n| S03 Транспорт | маршрут, груз, вес/объём, даты, погрузка |\n| S04 Складские услуги | товар, объём, период, операции, условия хранения |\n| S05 IT-разработка | бизнес-требования, интеграции, результат, приёмка |\n| S06 Маркетинг | цель, аудитория, каналы, география, KPI |\n| S07 Дизайн | материалы, форматы, брендбук, сроки, права |\n| S08 Мероприятия | дата, место, участники, программа, состав услуг |\n| S09 Обучение | тема, аудитория, участники, формат, результат |\n| S11 Консалтинг | проблема, результат, объём, формат отчёта |\n| S13 Полиграфия | макет, формат, тираж, материалы, цветность |\n| S14 Аренда | объект, период, место, характеристики, услуги |\n\n## Формальные проверки\n\n- дата не в прошлом;\n- количество больше нуля;\n- сумма неотрицательная;\n- единица измерения указана;\n- окончание не раньше начала;\n- сумма заявки согласована с позициями;\n- при запрете эквивалента есть обоснование;\n- при срочности есть причина;\n- при внебюджетной закупке указан статус согласования.\n",
    "sha256": "ce9361d9b28d830658c097377d911e625d435895091337a45b29944d646a1aab",
    "status": "active",
    "title": "Матрица обязательных полей",
    "version": "1.0"
  },
  {
    "content_without_front_matter": "# Правила срочности и приоритета\n\n## Нормативные сроки\n\nСрок считается от передачи полной заявки в отдел закупок.\n\n| Категория | Нормативный срок |\n|---|---:|\n| Стандартный серийный товар | 10 рабочих дней |\n| Технически сложный товар | 20 рабочих дней |\n| Индивидуальное производство | 30 рабочих дней |\n| Простая типовая услуга | 15 рабочих дней |\n| Сложная профессиональная услуга | 25 рабочих дней |\n| IT-разработка | 30 рабочих дней |\n| Мероприятие | 30 календарных дней |\n| Полиграфия по готовому макету | 10 рабочих дней |\n| Полиграфия с разработкой макета | 20 рабочих дней |\n\nСроки ориентировочные и не гарантируют поставку.\n\n## Приоритеты\n\n### P1 — критический\n\nПрименяется при угрозе безопасности, остановке критического процесса, существенном нарушении обязательств перед клиентами или аварии.\n\n### P2 — высокий\n\nПрименяется при сроке меньше нормативного, риске заметных финансовых потерь, срыве мероприятия или серьёзном сбое.\n\n### P3 — стандартный\n\nОбычная заявка, поданная с учётом нормативного срока.\n\n### P4 — низкий\n\nПотребность не влияет на текущую работу и может быть объединена с другими закупками.\n\n## Обязательные данные для срочной заявки\n\n- причина срочности;\n- дата возникновения потребности;\n- почему заявка не была подана раньше;\n- последствия задержки;\n- крайняя допустимая дата;\n- временная альтернатива;\n- подтверждение руководителя.\n\nАссистент определяет только предварительный приоритет. Окончательное решение принимает отдел закупок.\n",
    "document_id": "kb-006",
    "document_type": "urgency_rules",
    "effective_date": "2026-07-21",
    "filename": "06_Правила_срочности_и_приоритета.md",
    "language": "ru",
    "owner": "Отдел закупок",
    "priority": 6,
    "raw_content": "---\ndocument_id: kb-006\ntitle: Правила срочности и приоритета\ndocument_type: urgency_rules\nversion: \"1.0\"\neffective_date: \"2026-07-21\"\nowner: Отдел закупок\npriority: 6\nstatus: active\nlanguage: ru\n---\n\n# Правила срочности и приоритета\n\n## Нормативные сроки\n\nСрок считается от передачи полной заявки в отдел закупок.\n\n| Категория | Нормативный срок |\n|---|---:|\n| Стандартный серийный товар | 10 рабочих дней |\n| Технически сложный товар | 20 рабочих дней |\n| Индивидуальное производство | 30 рабочих дней |\n| Простая типовая услуга | 15 рабочих дней |\n| Сложная профессиональная услуга | 25 рабочих дней |\n| IT-разработка | 30 рабочих дней |\n| Мероприятие | 30 календарных дней |\n| Полиграфия по готовому макету | 10 рабочих дней |\n| Полиграфия с разработкой макета | 20 рабочих дней |\n\nСроки ориентировочные и не гарантируют поставку.\n\n## Приоритеты\n\n### P1 — критический\n\nПрименяется при угрозе безопасности, остановке критического процесса, существенном нарушении обязательств перед клиентами или аварии.\n\n### P2 — высокий\n\nПрименяется при сроке меньше нормативного, риске заметных финансовых потерь, срыве мероприятия или серьёзном сбое.\n\n### P3 — стандартный\n\nОбычная заявка, поданная с учётом нормативного срока.\n\n### P4 — низкий\n\nПотребность не влияет на текущую работу и может быть объединена с другими закупками.\n\n## Обязательные данные для срочной заявки\n\n- причина срочности;\n- дата возникновения потребности;\n- почему заявка не была подана раньше;\n- последствия задержки;\n- крайняя допустимая дата;\n- временная альтернатива;\n- подтверждение руководителя.\n\nАссистент определяет только предварительный приоритет. Окончательное решение принимает отдел закупок.\n",
    "sha256": "33eb7d4d96ff54aa6223e9d3bbc85f800875604b6e49a215ccc09d4bf3c29131",
    "status": "active",
    "title": "Правила срочности и приоритета",
    "version": "1.0"
  },
  {
    "content_without_front_matter": "# Статусы заявки и переходы\n\n| Статус | Значение | Кто устанавливает |\n|---|---|---|\n| Черновик | Заявка заполняется | Ассистент / инициатор |\n| Передана в отдел закупок | Подтверждена и зарегистрирована | Ассистент |\n| Требует доработки | Нужны сведения заказчика | Закупщик |\n| Принята в работу | Полнота подтверждена | Закупщик |\n| На согласовании | Требуется решение | Закупщик / система |\n| В работе | Проводится закупочная процедура | Закупщик |\n| Поставка ожидается | Поставщик выбран | Закупщик |\n| Выполнена | Товар или услуга получены | Закупщик |\n| Отклонена | Закупка не согласована | Согласующий |\n| Отменена заказчиком | Потребность отменена | Инициатор / закупщик |\n\n## Допустимые переходы\n\n```text\nЧерновик\n  → Передана в отдел закупок\n  → Отменена заказчиком\n\nПередана в отдел закупок\n  → Требует доработки\n  → Принята в работу\n  → На согласовании\n  → Отклонена\n  → Отменена заказчиком\n\nТребует доработки\n  → Передана в отдел закупок\n  → Отменена заказчиком\n\nПринята в работу\n  → На согласовании\n  → В работе\n  → Отклонена\n\nНа согласовании\n  → Принята в работу\n  → В работе\n  → Отклонена\n\nВ работе\n  → Поставка ожидается\n  → Отклонена\n\nПоставка ожидается\n  → Выполнена\n```\n\nКаждый переход сохраняется с датой, автором и комментарием.\n",
    "document_id": "kb-007",
    "document_type": "status_guide",
    "effective_date": "2026-07-21",
    "filename": "07_Статусы_и_переходы.md",
    "language": "ru",
    "owner": "Отдел закупок",
    "priority": 4,
    "raw_content": "---\ndocument_id: kb-007\ntitle: Статусы заявки и переходы\ndocument_type: status_guide\nversion: \"1.0\"\neffective_date: \"2026-07-21\"\nowner: Отдел закупок\npriority: 4\nstatus: active\nlanguage: ru\n---\n\n# Статусы заявки и переходы\n\n| Статус | Значение | Кто устанавливает |\n|---|---|---|\n| Черновик | Заявка заполняется | Ассистент / инициатор |\n| Передана в отдел закупок | Подтверждена и зарегистрирована | Ассистент |\n| Требует доработки | Нужны сведения заказчика | Закупщик |\n| Принята в работу | Полнота подтверждена | Закупщик |\n| На согласовании | Требуется решение | Закупщик / система |\n| В работе | Проводится закупочная процедура | Закупщик |\n| Поставка ожидается | Поставщик выбран | Закупщик |\n| Выполнена | Товар или услуга получены | Закупщик |\n| Отклонена | Закупка не согласована | Согласующий |\n| Отменена заказчиком | Потребность отменена | Инициатор / закупщик |\n\n## Допустимые переходы\n\n```text\nЧерновик\n  → Передана в отдел закупок\n  → Отменена заказчиком\n\nПередана в отдел закупок\n  → Требует доработки\n  → Принята в работу\n  → На согласовании\n  → Отклонена\n  → Отменена заказчиком\n\nТребует доработки\n  → Передана в отдел закупок\n  → Отменена заказчиком\n\nПринята в работу\n  → На согласовании\n  → В работе\n  → Отклонена\n\nНа согласовании\n  → Принята в работу\n  → В работе\n  → Отклонена\n\nВ работе\n  → Поставка ожидается\n  → Отклонена\n\nПоставка ожидается\n  → Выполнена\n```\n\nКаждый переход сохраняется с датой, автором и комментарием.\n",
    "sha256": "f2cd8b55b1b643634876baa27c3e31393cd4e7e1c681c4cf278aa8b2b539208e",
    "status": "active",
    "title": "Статусы заявки и переходы",
    "version": "1.0"
  },
  {
    "content_without_front_matter": "# Роли и ответственность\n\nОбозначения: **R** — выполняет, **A** — отвечает за результат, **C** — консультирует, **I** — информируется.\n\n| Этап | Инициатор | Руководитель | Закупки | Рук. закупок | Финансы | Эксперт | Склад |\n|---|---|---|---|---|---|---|---|\n| Формирование потребности | R | A | C | I | I | C | I |\n| Подготовка характеристик | R/A | I | C | I | I | C | I |\n| Проверка полноты | C | I | R/A | I | I | C | I |\n| Подтверждение срочности | R | A | C | I | I | I | I |\n| Проверка бюджета | C | I | I | I | R/A | I | I |\n| Выбор способа закупки | I | I | R | A | C | C | I |\n| Оценка технической части | R | I | C | I | I | A/C | I |\n| Выбор поставщика | C | I | R | A | C | C | I |\n| Приёмка | A/R | I | C | I | I | C | R/C |\n| Закрытие заявки | C | I | R/A | I | I | I | C |\n\nАссистент помогает собрать сведения, но не заменяет ответственных участников.\n",
    "document_id": "kb-008",
    "document_type": "responsibility_matrix",
    "effective_date": "2026-07-21",
    "filename": "08_Роли_и_ответственность.md",
    "language": "ru",
    "owner": "Отдел закупок",
    "priority": 9,
    "raw_content": "---\ndocument_id: kb-008\ntitle: Роли и ответственность\ndocument_type: responsibility_matrix\nversion: \"1.0\"\neffective_date: \"2026-07-21\"\nowner: Отдел закупок\npriority: 9\nstatus: active\nlanguage: ru\n---\n\n# Роли и ответственность\n\nОбозначения: **R** — выполняет, **A** — отвечает за результат, **C** — консультирует, **I** — информируется.\n\n| Этап | Инициатор | Руководитель | Закупки | Рук. закупок | Финансы | Эксперт | Склад |\n|---|---|---|---|---|---|---|---|\n| Формирование потребности | R | A | C | I | I | C | I |\n| Подготовка характеристик | R/A | I | C | I | I | C | I |\n| Проверка полноты | C | I | R/A | I | I | C | I |\n| Подтверждение срочности | R | A | C | I | I | I | I |\n| Проверка бюджета | C | I | I | I | R/A | I | I |\n| Выбор способа закупки | I | I | R | A | C | C | I |\n| Оценка технической части | R | I | C | I | I | A/C | I |\n| Выбор поставщика | C | I | R | A | C | C | I |\n| Приёмка | A/R | I | C | I | I | C | R/C |\n| Закрытие заявки | C | I | R/A | I | I | I | C |\n\nАссистент помогает собрать сведения, но не заменяет ответственных участников.\n",
    "sha256": "e5aa96b0a38a1db87d38615afb01c8451d982658409521cb029de8eb02a9ddd0",
    "status": "active",
    "title": "Роли и ответственность",
    "version": "1.0"
  },
  {
    "content_without_front_matter": "# Правила согласования заявок\n\n## Матрица согласования\n\n| Условие | Согласующие |\n|---|---|\n| Бюджетная закупка до 100 000 руб. | Руководитель подразделения |\n| Бюджетная закупка 100 001–500 000 руб. | Руководитель + финансовый контролёр |\n| Бюджетная закупка свыше 500 000 руб. | Руководитель + финансы + руководитель закупок |\n| Внебюджетная до 100 000 руб. | Руководитель + финансовый директор |\n| Внебюджетная свыше 100 000 руб. | Руководитель + финансовый директор + генеральный директор |\n| Срочная P1/P2 | Руководитель подразделения + руководитель закупок |\n| Единственный поставщик | Руководитель + руководитель закупок; свыше 500 000 руб. также финансы |\n| IT с доступом к данным | IT / информационная безопасность |\n| Юридические услуги | Юридическая служба |\n| Работы на объекте | АХО / охрана труда |\n\nАссистент может определить предварительный маршрут и проверить наличие обоснований, но не может одобрять заявку или считать согласование полученным со слов пользователя.\n\nРекомендуемый срок ответа одного согласующего — один рабочий день.\n",
    "document_id": "kb-009",
    "document_type": "approval_rules",
    "effective_date": "2026-07-21",
    "filename": "09_Правила_согласования.md",
    "language": "ru",
    "owner": "Отдел закупок",
    "priority": 5,
    "raw_content": "---\ndocument_id: kb-009\ntitle: Правила согласования заявок\ndocument_type: approval_rules\nversion: \"1.0\"\neffective_date: \"2026-07-21\"\nowner: Отдел закупок\npriority: 5\nstatus: active\nlanguage: ru\n---\n\n# Правила согласования заявок\n\n## Матрица согласования\n\n| Условие | Согласующие |\n|---|---|\n| Бюджетная закупка до 100 000 руб. | Руководитель подразделения |\n| Бюджетная закупка 100 001–500 000 руб. | Руководитель + финансовый контролёр |\n| Бюджетная закупка свыше 500 000 руб. | Руководитель + финансы + руководитель закупок |\n| Внебюджетная до 100 000 руб. | Руководитель + финансовый директор |\n| Внебюджетная свыше 100 000 руб. | Руководитель + финансовый директор + генеральный директор |\n| Срочная P1/P2 | Руководитель подразделения + руководитель закупок |\n| Единственный поставщик | Руководитель + руководитель закупок; свыше 500 000 руб. также финансы |\n| IT с доступом к данным | IT / информационная безопасность |\n| Юридические услуги | Юридическая служба |\n| Работы на объекте | АХО / охрана труда |\n\nАссистент может определить предварительный маршрут и проверить наличие обоснований, но не может одобрять заявку или считать согласование полученным со слов пользователя.\n\nРекомендуемый срок ответа одного согласующего — один рабочий день.\n",
    "sha256": "122c5d855252be71ec42f4e1cd507e2f8c2dee2f72b65932f15341acd9579777",
    "status": "active",
    "title": "Правила согласования заявок",
    "version": "1.0"
  },
  {
    "content_without_front_matter": "# FAQ внутренних заказчиков\n\n## Подача заявки\n\n### Что считается официальной заявкой?\nЗаявка, подтверждённая через ассистента, получившая номер и статус `Передана в отдел закупок`.\n\n### Можно ли попросить закупщика устно?\nОбсудить можно, но устная просьба не заменяет регистрацию.\n\n### Можно ли создать одну заявку на разные товары?\nДа, если они относятся к одной категории и могут закупаться совместно.\n\n### Можно ли сохранить заявку и продолжить позже?\nДа, как черновик.\n\n## Требования\n\n### Кто отвечает за характеристики?\nВнутренний заказчик или профильный эксперт.\n\n### Почему ассистент задаёт вопросы?\nОн сравнивает заявку с обязательными полями по категории.\n\n### Можно ли указать ссылку вместо характеристик?\nНет. Ссылка — только референс.\n\n### Что написать в обосновании?\nБизнес-задачу, последствия отсутствия закупки и связь с работой подразделения.\n\n## Сроки\n\n### Что делать, если срок меньше нормативного?\nУказать причину, последствия и получить подтверждение руководителя.\n\n### Гарантирует ли высокий приоритет быструю поставку?\nНет. Он означает приоритетную обработку.\n\n## Бюджет\n\n### Какую сумму указывать?\nОбщую ориентировочную стоимость заявки.\n\n### Что делать, если стоимость неизвестна?\nУказать диапазон или рыночный ориентир.\n\n### Можно ли подать внебюджетную заявку?\nДа, но потребуется дополнительное согласование.\n\n## Бренды и поставщики\n\n### Можно ли указать бренд?\nДа, как референс с «или эквивалент». Запрет эквивалента нужно обосновать.\n\n### Можно ли предложить поставщика?\nДа, но окончательное решение принимает уполномоченный участник процесса.\n\n### Достаточно ли написать «мы всегда у него покупаем»?\nНет.\n\n## Статусы\n\n### Что означает «Требует доработки»?\nЗакупщик указал, какие сведения нужно дополнить.\n\n### Кто обновляет статус?\nОтветственный сотрудник отдела закупок.\n\n### Сохранится ли номер после доработки?\nДа.\n\n## Работа ассистента\n\n### Может ли ассистент выбрать поставщика?\nНет.\n\n### Что делать, если ассистент не знает ответа?\nОн должен сообщить об этом и направить пользователя в отдел закупок.\n\n### Какие данные нельзя отправлять?\nПаспортные данные, банковские реквизиты, пароли и избыточную конфиденциальную информацию.\n",
    "document_id": "kb-010",
    "document_type": "faq",
    "effective_date": "2026-07-21",
    "filename": "10_FAQ_внутренних_заказчиков.md",
    "language": "ru",
    "owner": "Отдел закупок",
    "priority": 7,
    "raw_content": "---\ndocument_id: kb-010\ntitle: FAQ внутренних заказчиков\ndocument_type: faq\nversion: \"1.0\"\neffective_date: \"2026-07-21\"\nowner: Отдел закупок\npriority: 7\nstatus: active\nlanguage: ru\n---\n\n# FAQ внутренних заказчиков\n\n## Подача заявки\n\n### Что считается официальной заявкой?\nЗаявка, подтверждённая через ассистента, получившая номер и статус `Передана в отдел закупок`.\n\n### Можно ли попросить закупщика устно?\nОбсудить можно, но устная просьба не заменяет регистрацию.\n\n### Можно ли создать одну заявку на разные товары?\nДа, если они относятся к одной категории и могут закупаться совместно.\n\n### Можно ли сохранить заявку и продолжить позже?\nДа, как черновик.\n\n## Требования\n\n### Кто отвечает за характеристики?\nВнутренний заказчик или профильный эксперт.\n\n### Почему ассистент задаёт вопросы?\nОн сравнивает заявку с обязательными полями по категории.\n\n### Можно ли указать ссылку вместо характеристик?\nНет. Ссылка — только референс.\n\n### Что написать в обосновании?\nБизнес-задачу, последствия отсутствия закупки и связь с работой подразделения.\n\n## Сроки\n\n### Что делать, если срок меньше нормативного?\nУказать причину, последствия и получить подтверждение руководителя.\n\n### Гарантирует ли высокий приоритет быструю поставку?\nНет. Он означает приоритетную обработку.\n\n## Бюджет\n\n### Какую сумму указывать?\nОбщую ориентировочную стоимость заявки.\n\n### Что делать, если стоимость неизвестна?\nУказать диапазон или рыночный ориентир.\n\n### Можно ли подать внебюджетную заявку?\nДа, но потребуется дополнительное согласование.\n\n## Бренды и поставщики\n\n### Можно ли указать бренд?\nДа, как референс с «или эквивалент». Запрет эквивалента нужно обосновать.\n\n### Можно ли предложить поставщика?\nДа, но окончательное решение принимает уполномоченный участник процесса.\n\n### Достаточно ли написать «мы всегда у него покупаем»?\nНет.\n\n## Статусы\n\n### Что означает «Требует доработки»?\nЗакупщик указал, какие сведения нужно дополнить.\n\n### Кто обновляет статус?\nОтветственный сотрудник отдела закупок.\n\n### Сохранится ли номер после доработки?\nДа.\n\n## Работа ассистента\n\n### Может ли ассистент выбрать поставщика?\nНет.\n\n### Что делать, если ассистент не знает ответа?\nОн должен сообщить об этом и направить пользователя в отдел закупок.\n\n### Какие данные нельзя отправлять?\nПаспортные данные, банковские реквизиты, пароли и избыточную конфиденциальную информацию.\n",
    "sha256": "317644d05521d2b93490a931b32a197629e4ced19844d69b003297291c091a41",
    "status": "active",
    "title": "FAQ внутренних заказчиков",
    "version": "1.0"
  },
  {
    "content_without_front_matter": "# Примеры корректных и некорректных заявок\n\n## 1. Некорректная заявка на товар\n\n> Срочно нужны хорошие ноутбуки, как у маркетинга.\n\nНе хватает количества, характеристик, даты, бюджета, места поставки и обоснования срочности.\n\n## 2. Корректная заявка на товар\n\n> Требуется 5 ноутбуков для новых менеджеров. RAM от 16 ГБ, SSD от 512 ГБ, Windows 11 Pro, вес до 1,8 кг. Допустимы Lenovo, HP, Dell или эквивалент. Получить в центральный офис до 15.09.2026. Бюджет до 500 000 руб.\n\nНужно уточнить только бизнес-обоснование и статью бюджета.\n\n## 3. Некорректная заявка на услугу\n\n> Нужно красиво оформить стенд и сделать быстро.\n\nНе хватает даты, размеров, состава работ, результата, бюджета и критериев приёмки.\n\n## 4. Корректная услуга\n\n> Разработать дизайн стенда 6×3 м к выставке 10.10.2026: три концепции, доработка выбранной, адаптация для шести носителей и передача исходников. Брендбук приложен. Бюджет до 200 000 руб.\n\n## 5. Необоснованная срочность\n\n> Сломался принтер, купите новый завтра.\n\nНужно уточнить модель, объём печати, возможность ремонта, временную альтернативу, бюджет и подтверждение руководителя.\n\n## 6. Бренд без обоснования\n\n> Купить 10 мониторов только Samsung.\n\nАссистент спрашивает, допустим ли эквивалент. При запрете просит обоснование.\n\n## 7. Несвязанные категории\n\n> Нужны кресла, лицензия Photoshop и доставка документов.\n\nСоздаются три отдельные заявки.\n\n## 8. Ошибка в сумме\n\n> 20 коробок по 1 500 руб., общий бюджет 20 000 руб.\n\nРасчётная сумма — 30 000 руб. Ассистент просит исправить.\n\n## 9. Субъективная приёмка\n\n> Провести хороший тренинг, чтобы всем понравилось.\n\nНужно уточнить тему, аудиторию, число участников, формат и ожидаемый результат.\n\n## 10. Корректная перевозка\n\n> Перевезти 12 паллет весом около 4 тонн со склада в Химках на выставку в Москве 04.09.2026. Нужна машина с гидробортом. Бюджет до 35 000 руб.\n\n## 11. Необоснованный поставщик\n\n> Заказать у ООО «Альфа», потому что с ними удобно.\n\nУдобство не является достаточным основанием для единственного поставщика.\n\n## 12. Обоснованная оригинальная запчасть\n\n> Нужен оригинальный ремень XZ-440 для конвейера LinePro 12, 2 шт. Эквивалент запрещён из-за гарантии производителя. Письмо приложено.\n\n## 13. Нет единицы измерения\n\n> Заказать упаковочную плёнку, количество 100.\n\nАссистент уточняет: рулонов, метров, килограммов или упаковок.\n\n## 14. Дата в прошлом\n\nАссистент просит указать актуальную дату.\n\n## 15. Корректная IT-услуга\n\n> Интегрировать форму заявок со справочником сотрудников. Результат: получение ФИО, подразделения и email по Telegram ID. Нужны документация, журнал ошибок и тесты. Срок до 30.11.2026. Бюджет до 350 000 руб.\n",
    "document_id": "kb-011",
    "document_type": "examples",
    "effective_date": "2026-07-21",
    "filename": "11_Примеры_заявок.md",
    "language": "ru",
    "owner": "Отдел закупок",
    "priority": 8,
    "raw_content": "---\ndocument_id: kb-011\ntitle: Примеры корректных и некорректных заявок\ndocument_type: examples\nversion: \"1.0\"\neffective_date: \"2026-07-21\"\nowner: Отдел закупок\npriority: 8\nstatus: active\nlanguage: ru\n---\n\n# Примеры корректных и некорректных заявок\n\n## 1. Некорректная заявка на товар\n\n> Срочно нужны хорошие ноутбуки, как у маркетинга.\n\nНе хватает количества, характеристик, даты, бюджета, места поставки и обоснования срочности.\n\n## 2. Корректная заявка на товар\n\n> Требуется 5 ноутбуков для новых менеджеров. RAM от 16 ГБ, SSD от 512 ГБ, Windows 11 Pro, вес до 1,8 кг. Допустимы Lenovo, HP, Dell или эквивалент. Получить в центральный офис до 15.09.2026. Бюджет до 500 000 руб.\n\nНужно уточнить только бизнес-обоснование и статью бюджета.\n\n## 3. Некорректная заявка на услугу\n\n> Нужно красиво оформить стенд и сделать быстро.\n\nНе хватает даты, размеров, состава работ, результата, бюджета и критериев приёмки.\n\n## 4. Корректная услуга\n\n> Разработать дизайн стенда 6×3 м к выставке 10.10.2026: три концепции, доработка выбранной, адаптация для шести носителей и передача исходников. Брендбук приложен. Бюджет до 200 000 руб.\n\n## 5. Необоснованная срочность\n\n> Сломался принтер, купите новый завтра.\n\nНужно уточнить модель, объём печати, возможность ремонта, временную альтернативу, бюджет и подтверждение руководителя.\n\n## 6. Бренд без обоснования\n\n> Купить 10 мониторов только Samsung.\n\nАссистент спрашивает, допустим ли эквивалент. При запрете просит обоснование.\n\n## 7. Несвязанные категории\n\n> Нужны кресла, лицензия Photoshop и доставка документов.\n\nСоздаются три отдельные заявки.\n\n## 8. Ошибка в сумме\n\n> 20 коробок по 1 500 руб., общий бюджет 20 000 руб.\n\nРасчётная сумма — 30 000 руб. Ассистент просит исправить.\n\n## 9. Субъективная приёмка\n\n> Провести хороший тренинг, чтобы всем понравилось.\n\nНужно уточнить тему, аудиторию, число участников, формат и ожидаемый результат.\n\n## 10. Корректная перевозка\n\n> Перевезти 12 паллет весом около 4 тонн со склада в Химках на выставку в Москве 04.09.2026. Нужна машина с гидробортом. Бюджет до 35 000 руб.\n\n## 11. Необоснованный поставщик\n\n> Заказать у ООО «Альфа», потому что с ними удобно.\n\nУдобство не является достаточным основанием для единственного поставщика.\n\n## 12. Обоснованная оригинальная запчасть\n\n> Нужен оригинальный ремень XZ-440 для конвейера LinePro 12, 2 шт. Эквивалент запрещён из-за гарантии производителя. Письмо приложено.\n\n## 13. Нет единицы измерения\n\n> Заказать упаковочную плёнку, количество 100.\n\nАссистент уточняет: рулонов, метров, килограммов или упаковок.\n\n## 14. Дата в прошлом\n\nАссистент просит указать актуальную дату.\n\n## 15. Корректная IT-услуга\n\n> Интегрировать форму заявок со справочником сотрудников. Результат: получение ФИО, подразделения и email по Telegram ID. Нужны документация, журнал ошибок и тесты. Срок до 30.11.2026. Бюджет до 350 000 руб.\n",
    "sha256": "ab422607a03fb749ba8714b098d8fb22836441ffc245fea1d12b8c2f7da4c6cd",
    "status": "active",
    "title": "Примеры корректных и некорректных заявок",
    "version": "1.0"
  },
  {
    "content_without_front_matter": "# Глоссарий\n\n**Бюджетная закупка** — закупка, предусмотренная утверждённым бюджетом.\n\n**Внебюджетная закупка** — закупка, требующая дополнительного согласования.\n\n**Внутренний заказчик** — сотрудник, инициирующий закупку.\n\n**Единственный поставщик** — поставщик без конкурентного сравнения при наличии основания.\n\n**Заявка на закупку** — структурированный запрос для начала закупки.\n\n**Закупочная категория** — группа сходных товаров или услуг.\n\n**Критерии приёмки** — проверяемые условия оценки результата.\n\n**Ориентировочный бюджет** — ожидаемая общая стоимость.\n\n**Референс** — пример, поясняющий ожидания.\n\n**Спецификация** — перечень позиций и характеристик.\n\n**Срочная заявка** — заявка со сроком меньше нормативного и обоснованной срочностью.\n\n**Техническое задание** — описание предмета, результата, условий и критериев приёмки.\n\n**Эквивалент** — сопоставимый по требуемым характеристикам товар или решение.\n",
    "document_id": "kb-012",
    "document_type": "glossary",
    "effective_date": "2026-07-21",
    "filename": "12_Глоссарий.md",
    "language": "ru",
    "owner": "Отдел закупок",
    "priority": 9,
    "raw_content": "---\ndocument_id: kb-012\ntitle: Глоссарий\ndocument_type: glossary\nversion: \"1.0\"\neffective_date: \"2026-07-21\"\nowner: Отдел закупок\npriority: 9\nstatus: active\nlanguage: ru\n---\n\n# Глоссарий\n\n**Бюджетная закупка** — закупка, предусмотренная утверждённым бюджетом.\n\n**Внебюджетная закупка** — закупка, требующая дополнительного согласования.\n\n**Внутренний заказчик** — сотрудник, инициирующий закупку.\n\n**Единственный поставщик** — поставщик без конкурентного сравнения при наличии основания.\n\n**Заявка на закупку** — структурированный запрос для начала закупки.\n\n**Закупочная категория** — группа сходных товаров или услуг.\n\n**Критерии приёмки** — проверяемые условия оценки результата.\n\n**Ориентировочный бюджет** — ожидаемая общая стоимость.\n\n**Референс** — пример, поясняющий ожидания.\n\n**Спецификация** — перечень позиций и характеристик.\n\n**Срочная заявка** — заявка со сроком меньше нормативного и обоснованной срочностью.\n\n**Техническое задание** — описание предмета, результата, условий и критериев приёмки.\n\n**Эквивалент** — сопоставимый по требуемым характеристикам товар или решение.\n",
    "sha256": "039ad328498f0e36ad7439d131135dd153ab22643f511f24726da9e0161634e7",
    "status": "active",
    "title": "Глоссарий",
    "version": "1.0"
  },
  {
    "content_without_front_matter": "# Инструкция по работе с ассистентом\n\n## 1. Назначение ассистента\n\nИИ-ассистент помогает сотрудникам ООО «Вектор Дистрибуция» оформлять заявки на нерегулярные закупки товаров и услуг, а также отвечает на вопросы по правилам подачи и обработки заявок.\n\nАссистент предназначен для предварительной подготовки заявки. Он помогает собрать обязательные сведения, проверить полноту данных и сформировать итоговую карточку для передачи в отдел закупок.\n\nАссистент не принимает решение о необходимости закупки, не подтверждает бюджет, не согласовывает заявку и не выбирает поставщика.\n\n## 2. Какие задачи выполняет ассистент\n\nАссистент может:\n\n- принять описание потребности в свободной форме;\n- определить, относится заявка к товару или услуге;\n- предложить подходящую закупочную категорию;\n- извлечь уже указанные сведения;\n- последовательно запросить недостающие данные;\n- проверить формальную полноту заявки;\n- помочь уточнить характеристики товара или результат услуги;\n- сформировать итоговую карточку заявки;\n- сохранить незавершённую заявку как черновик;\n- продолжить ранее сохранённый черновик;\n- ответить на вопросы по внутренним правилам закупочного процесса;\n- указать документ, на котором основан ответ;\n- направить нестандартный вопрос сотруднику отдела закупок.\n\n## 3. Как создать новую заявку\n\nЧтобы начать оформление, опишите потребность обычными словами.\n\nПример:\n\n> Нужно купить 10 мониторов для нового отдела продаж к 15 августа. Диагональ не меньше 24 дюймов, подключение HDMI, бюджет около 250 000 рублей.\n\nНеобязательно сразу знать все поля. Ассистент извлечёт сведения из сообщения и задаст вопросы только по тому, чего не хватает.\n\nДля начала новой заявки также можно использовать команду `/new`.\n\n## 4. Как отвечать на уточняющие вопросы\n\nАссистент задаёт вопросы последовательно. Отвечайте на текущий вопрос настолько точно, насколько это возможно.\n\nЕсли точные данные пока неизвестны:\n\n- укажите ориентировочное значение или диапазон;\n- назовите сотрудника, который может подтвердить требования;\n- приложите техническое задание, когда загрузка файлов будет доступна;\n- сохраните заявку как черновик и продолжите позже.\n\nНе нужно повторять всю заявку в каждом сообщении. Достаточно ответить на заданный вопрос.\n\n## 5. Какие сведения обычно требуются\n\nДля товара обычно нужны:\n\n- наименование и назначение;\n- количество;\n- единица измерения;\n- обязательные характеристики;\n- требования к совместимости;\n- требуемая дата;\n- место поставки;\n- ориентировочный бюджет;\n- допустимость эквивалента;\n- дополнительные поля выбранной категории.\n\nДля услуги обычно нужны:\n\n- ожидаемый результат;\n- состав и объём работ;\n- период оказания;\n- место оказания;\n- требования к исполнителю;\n- критерии приёмки;\n- ориентировочный бюджет;\n- дополнительные поля выбранной категории.\n\nТочный перечень зависит от закупочной категории.\n\n## 6. Как сохранить и продолжить черновик\n\nПромежуточные данные заявки сохраняются как черновик.\n\nЕсли оформление необходимо прервать:\n\n- сообщите ассистенту, что хотите продолжить позже;\n- используйте команду `/cancel`, чтобы завершить текущий диалог без регистрации;\n- используйте команду `/continue`, чтобы вернуться к последнему незавершённому черновику.\n\nЧерновик не считается зарегистрированной заявкой и не передаётся в отдел закупок.\n\n## 7. Как подтвердить заявку\n\nПосле заполнения обязательных полей ассистент показывает итоговую карточку.\n\nПеред подтверждением проверьте:\n\n- предмет закупки;\n- количество или объём;\n- характеристики или состав работ;\n- даты;\n- место поставки или оказания услуги;\n- бюджет;\n- срочность;\n- допустимость эквивалента;\n- контактные сведения.\n\nЗаявка регистрируется только после явного подтверждения пользователя и успешного сохранения системой.\n\nПосле регистрации заявке присваивается уникальный номер и статус `Передана в отдел закупок`.\n\n## 8. Как задать справочный вопрос\n\nМожно задать вопрос по закупочному процессу без создания заявки.\n\nТемы справочных вопросов:\n\n- обязательные поля;\n- статусы заявки;\n- правила согласования;\n- бренды и эквиваленты;\n- работа с черновиком.\n\nАссистент отвечает на основании базы знаний и при необходимости указывает источник.\n\n## 9. Что делать, если ответа нет\n\nЕсли в базе знаний нет подтверждённой информации, ассистент не придумывает правило.\n\nВ таком случае он:\n\n- сообщает, что подтверждённой информации нет;\n- при необходимости задаёт уточняющий вопрос;\n- предлагает обратиться к сотруднику отдела закупок;\n- может подсказать, какой договор, регламент или другой первичный документ следует проверить.\n\nНестандартные случаи передаются на ручное рассмотрение.\n\n## 10. Какие сведения нельзя передавать\n\nНе передавайте через ассистента:\n\n- пароли и коды доступа;\n- паспортные данные;\n- банковские реквизиты физических лиц;\n- платёжные данные;\n- закрытые договоры без разрешения;\n- коммерческие предложения с конфиденциальными условиями;\n- персональные данные, не требующиеся для оформления заявки;\n- секретные ключи, токены и данные доступа к корпоративным системам.\n\nЕсли чувствительные сведения не нужны для закупки, удалите или обезличьте их до отправки.\n\n## 11. Ограничения ассистента\n\nАссистент не может:\n\n- одобрить или отклонить закупку;\n- подтвердить наличие бюджета;\n- принять решение о целесообразности потребности;\n- профессионально подтвердить правильность технических требований;\n- выбрать поставщика;\n- провести тендер;\n- согласовать договор;\n- создать заказ поставщику;\n- провести оплату;\n- изменить данные в ERP, 1С или складской системе;\n- гарантировать выполнение срочной заявки в желаемый срок;\n- раскрыть пользователю чужие заявки или закрытые сведения.\n\nОтветственность за обоснованность потребности, количество, характеристики, сроки и достоверность данных остаётся у внутреннего заказчика.\n\n## 12. Если возникла техническая ошибка\n\nЕсли данные не удалось сохранить, ассистент не должен сообщать, что заявка зарегистрирована.\n\nВ этом случае:\n\n- повторите действие;\n- проверьте, сохранился ли черновик;\n- при повторной ошибке обратитесь в отдел закупок или к ответственному за поддержку системы.\n\nПередача заявки считается успешной только после получения её уникального номера.\n",
    "document_id": "kb-014",
    "document_type": "user_guide",
    "effective_date": "2026-07-23",
    "filename": "13_Инструкция_по_работе_с_ассистентом.md",
    "language": "ru",
    "owner": "Отдел закупок",
    "priority": 9,
    "raw_content": "---\ndocument_id: kb-014\ntitle: Инструкция по работе с ассистентом\ndocument_type: user_guide\nversion: \"1.0\"\neffective_date: \"2026-07-23\"\nowner: Отдел закупок\npriority: 9\nstatus: active\nlanguage: ru\n---\n\n# Инструкция по работе с ассистентом\n\n## 1. Назначение ассистента\n\nИИ-ассистент помогает сотрудникам ООО «Вектор Дистрибуция» оформлять заявки на нерегулярные закупки товаров и услуг, а также отвечает на вопросы по правилам подачи и обработки заявок.\n\nАссистент предназначен для предварительной подготовки заявки. Он помогает собрать обязательные сведения, проверить полноту данных и сформировать итоговую карточку для передачи в отдел закупок.\n\nАссистент не принимает решение о необходимости закупки, не подтверждает бюджет, не согласовывает заявку и не выбирает поставщика.\n\n## 2. Какие задачи выполняет ассистент\n\nАссистент может:\n\n- принять описание потребности в свободной форме;\n- определить, относится заявка к товару или услуге;\n- предложить подходящую закупочную категорию;\n- извлечь уже указанные сведения;\n- последовательно запросить недостающие данные;\n- проверить формальную полноту заявки;\n- помочь уточнить характеристики товара или результат услуги;\n- сформировать итоговую карточку заявки;\n- сохранить незавершённую заявку как черновик;\n- продолжить ранее сохранённый черновик;\n- ответить на вопросы по внутренним правилам закупочного процесса;\n- указать документ, на котором основан ответ;\n- направить нестандартный вопрос сотруднику отдела закупок.\n\n## 3. Как создать новую заявку\n\nЧтобы начать оформление, опишите потребность обычными словами.\n\nПример:\n\n> Нужно купить 10 мониторов для нового отдела продаж к 15 августа. Диагональ не меньше 24 дюймов, подключение HDMI, бюджет около 250 000 рублей.\n\nНеобязательно сразу знать все поля. Ассистент извлечёт сведения из сообщения и задаст вопросы только по тому, чего не хватает.\n\nДля начала новой заявки также можно использовать команду `/new`.\n\n## 4. Как отвечать на уточняющие вопросы\n\nАссистент задаёт вопросы последовательно. Отвечайте на текущий вопрос настолько точно, насколько это возможно.\n\nЕсли точные данные пока неизвестны:\n\n- укажите ориентировочное значение или диапазон;\n- назовите сотрудника, который может подтвердить требования;\n- приложите техническое задание, когда загрузка файлов будет доступна;\n- сохраните заявку как черновик и продолжите позже.\n\nНе нужно повторять всю заявку в каждом сообщении. Достаточно ответить на заданный вопрос.\n\n## 5. Какие сведения обычно требуются\n\nДля товара обычно нужны:\n\n- наименование и назначение;\n- количество;\n- единица измерения;\n- обязательные характеристики;\n- требования к совместимости;\n- требуемая дата;\n- место поставки;\n- ориентировочный бюджет;\n- допустимость эквивалента;\n- дополнительные поля выбранной категории.\n\nДля услуги обычно нужны:\n\n- ожидаемый результат;\n- состав и объём работ;\n- период оказания;\n- место оказания;\n- требования к исполнителю;\n- критерии приёмки;\n- ориентировочный бюджет;\n- дополнительные поля выбранной категории.\n\nТочный перечень зависит от закупочной категории.\n\n## 6. Как сохранить и продолжить черновик\n\nПромежуточные данные заявки сохраняются как черновик.\n\nЕсли оформление необходимо прервать:\n\n- сообщите ассистенту, что хотите продолжить позже;\n- используйте команду `/cancel`, чтобы завершить текущий диалог без регистрации;\n- используйте команду `/continue`, чтобы вернуться к последнему незавершённому черновику.\n\nЧерновик не считается зарегистрированной заявкой и не передаётся в отдел закупок.\n\n## 7. Как подтвердить заявку\n\nПосле заполнения обязательных полей ассистент показывает итоговую карточку.\n\nПеред подтверждением проверьте:\n\n- предмет закупки;\n- количество или объём;\n- характеристики или состав работ;\n- даты;\n- место поставки или оказания услуги;\n- бюджет;\n- срочность;\n- допустимость эквивалента;\n- контактные сведения.\n\nЗаявка регистрируется только после явного подтверждения пользователя и успешного сохранения системой.\n\nПосле регистрации заявке присваивается уникальный номер и статус `Передана в отдел закупок`.\n\n## 8. Как задать справочный вопрос\n\nМожно задать вопрос по закупочному процессу без создания заявки.\n\nТемы справочных вопросов:\n\n- обязательные поля;\n- статусы заявки;\n- правила согласования;\n- бренды и эквиваленты;\n- работа с черновиком.\n\nАссистент отвечает на основании базы знаний и при необходимости указывает источник.\n\n## 9. Что делать, если ответа нет\n\nЕсли в базе знаний нет подтверждённой информации, ассистент не придумывает правило.\n\nВ таком случае он:\n\n- сообщает, что подтверждённой информации нет;\n- при необходимости задаёт уточняющий вопрос;\n- предлагает обратиться к сотруднику отдела закупок;\n- может подсказать, какой договор, регламент или другой первичный документ следует проверить.\n\nНестандартные случаи передаются на ручное рассмотрение.\n\n## 10. Какие сведения нельзя передавать\n\nНе передавайте через ассистента:\n\n- пароли и коды доступа;\n- паспортные данные;\n- банковские реквизиты физических лиц;\n- платёжные данные;\n- закрытые договоры без разрешения;\n- коммерческие предложения с конфиденциальными условиями;\n- персональные данные, не требующиеся для оформления заявки;\n- секретные ключи, токены и данные доступа к корпоративным системам.\n\nЕсли чувствительные сведения не нужны для закупки, удалите или обезличьте их до отправки.\n\n## 11. Ограничения ассистента\n\nАссистент не может:\n\n- одобрить или отклонить закупку;\n- подтвердить наличие бюджета;\n- принять решение о целесообразности потребности;\n- профессионально подтвердить правильность технических требований;\n- выбрать поставщика;\n- провести тендер;\n- согласовать договор;\n- создать заказ поставщику;\n- провести оплату;\n- изменить данные в ERP, 1С или складской системе;\n- гарантировать выполнение срочной заявки в желаемый срок;\n- раскрыть пользователю чужие заявки или закрытые сведения.\n\nОтветственность за обоснованность потребности, количество, характеристики, сроки и достоверность данных остаётся у внутреннего заказчика.\n\n## 12. Если возникла техническая ошибка\n\nЕсли данные не удалось сохранить, ассистент не должен сообщать, что заявка зарегистрирована.\n\nВ этом случае:\n\n- повторите действие;\n- проверьте, сохранился ли черновик;\n- при повторной ошибке обратитесь в отдел закупок или к ответственному за поддержку системы.\n\nПередача заявки считается успешной только после получения её уникального номера.\n",
    "sha256": "fee7b3c099788bd9abcf7a14cd4b66a7211b39f8443c3140ab5b83629403fda3",
    "status": "active",
    "title": "Инструкция по работе с ассистентом",
    "version": "1.0"
  },
  {
    "content_without_front_matter": "# Типовые ошибки при оформлении заявок\n\n## 1. Слишком общее описание потребности\n\n### Почему это проблема\n\nФормулировки «нужно оборудование», «нужна реклама» или «заказать доставку» не позволяют определить предмет закупки, категорию и обязательные требования.\n\n### Как исправить\n\nУкажите, что именно требуется, для какой цели и какой результат ожидается.\n\n**Плохо:**\n\n> Нужно оборудование для офиса.\n\n**Хорошо:**\n\n> Нужно 5 ноутбуков для новых сотрудников отдела продаж. Они будут использоваться для офисных программ, видеоконференций и работы в CRM.\n\n## 2. Отсутствует количество или объём\n\n### Почему это проблема\n\nБез количества товара или объёма услуги невозможно оценить бюджет, сроки и способ закупки.\n\n### Как исправить\n\nУкажите числовое значение и единицу измерения. Для услуги опишите объём работ.\n\n**Плохо:**\n\n> Нужно заказать офисную бумагу.\n\n**Хорошо:**\n\n> Нужно заказать 100 пачек офисной бумаги формата A4 по 500 листов.\n\n## 3. Не указана единица измерения\n\n### Почему это проблема\n\nЧисло без единицы измерения может трактоваться по-разному: штуки, упаковки, комплекты, часы или месяцы.\n\n### Как исправить\n\nВсегда указывайте единицу измерения рядом с количеством.\n\n**Плохо:**\n\n> Требуется 20 кабелей.\n\n**Хорошо:**\n\n> Требуется 20 штук кабелей HDMI длиной 2 метра.\n\n## 4. Использованы субъективные требования\n\n### Почему это проблема\n\nФормулировки «качественный», «красивый», «современный» или «удобный» нельзя объективно проверить при выборе и приёмке.\n\n### Как исправить\n\nЗамените субъективные ожидания измеримыми характеристиками или критериями.\n\n**Плохо:**\n\n> Нужны красивые и удобные кресла.\n\n**Хорошо:**\n\n> Нужны офисные кресла с регулируемой высотой, поясничной поддержкой, подлокотниками и допустимой нагрузкой не менее 120 кг.\n\n## 5. Указана только ссылка на товар\n\n### Почему это проблема\n\nСтраница по ссылке может измениться или стать недоступной. Кроме того, ссылка не объясняет, какие характеристики действительно обязательны.\n\n### Как исправить\n\nИспользуйте ссылку как пример, но отдельно перечислите обязательные параметры.\n\n**Плохо:**\n\n> Купите вот это: https://example.com/product.\n\n**Хорошо:**\n\n> Ссылка приведена как референс. Обязательные характеристики: диагональ 24–27 дюймов, разрешение не ниже Full HD, HDMI, регулировка наклона.\n\n## 6. Указан конкретный бренд без обоснования\n\n### Почему это проблема\n\nНеобоснованное ограничение бренда сокращает конкуренцию и может увеличить стоимость или срок закупки.\n\n### Как исправить\n\nУкажите «или эквивалент». Если эквивалент недопустим, объясните объективную причину: совместимость, единый парк оборудования, требования гарантии или утверждённый стандарт.\n\n**Плохо:**\n\n> Нужны только мониторы Samsung.\n\n**Хорошо:**\n\n> Нужны мониторы Samsung или эквивалент с указанными характеристиками.\n\n**Хорошо при запрете эквивалента:**\n\n> Нужны терминалы конкретной модели, поскольку они должны работать с уже установленными док-станциями и корпоративным образом системы. Совместимость другой модели не подтверждена.\n\n## 7. Нет критериев приёмки услуги\n\n### Почему это проблема\n\nБез критериев приёмки невозможно однозначно определить, выполнена ли услуга и соответствует ли результат ожиданиям.\n\n### Как исправить\n\nОпишите конкретный результат и способ его проверки.\n\n**Плохо:**\n\n> Сделать качественную презентацию.\n\n**Хорошо:**\n\n> Подготовить презентацию на 15–20 слайдов в корпоративном шаблоне, передать редактируемый файл PPTX и PDF, устранить замечания после одного раунда согласования.\n\n## 8. Указана прошедшая или противоречивая дата\n\n### Почему это проблема\n\nПоставка не может быть запланирована на прошедшую дату, а окончание услуги не может быть раньше её начала.\n\n### Как исправить\n\nПроверьте календарные даты и учитывайте нормативный срок закупки.\n\n**Плохо:**\n\n> Подать заявку 20 июля, поставка нужна 15 июля.\n\n**Хорошо:**\n\n> Заявка подаётся 20 июля, требуемая дата поставки — 20 августа.\n\n## 9. Не указан бюджет или бюджетный статус\n\n### Почему это проблема\n\nБез ориентировочной суммы и понимания, предусмотрены ли расходы бюджетом, нельзя определить маршрут согласования и реалистичность потребности.\n\n### Как исправить\n\nУкажите точную сумму, диапазон или максимально допустимый бюджет, а также бюджетный статус.\n\n**Плохо:**\n\n> Стоимость пока неизвестна.\n\n**Хорошо:**\n\n> Ориентировочный бюджет — 180 000–220 000 рублей, закупка предусмотрена бюджетом отдела.\n\n## 10. Срочность не обоснована\n\n### Почему это проблема\n\nФраза «нужно срочно» не объясняет причину и не позволяет определить приоритет заявки.\n\n### Как исправить\n\nУкажите причину срочности, последствия задержки, дату возникновения потребности и наличие временной альтернативы.\n\n**Плохо:**\n\n> Нужно очень срочно, желательно завтра.\n\n**Хорошо:**\n\n> Поставка нужна до 5 августа, поскольку 6 августа открывается новая торговая точка. При задержке сотрудники не смогут начать работу. Временной альтернативы нет.\n\n## 11. В одной заявке объединены разные категории\n\n### Почему это проблема\n\nТовары и услуги разных категорий могут иметь разные требования, сроки, поставщиков и маршруты согласования.\n\n### Как исправить\n\nРазделите потребности на отдельные заявки по однородным категориям.\n\n**Плохо:**\n\n> В одной заявке нужны кресла, лицензии на программное обеспечение и курьерская доставка.\n\n**Хорошо:**\n\n> Создать три заявки: на офисные кресла, на программные лицензии и на курьерскую услугу.\n\nНесколько позиций можно объединить, если они относятся к одной категории и закупаются совместно.\n\n## 12. Переданы лишние чувствительные данные\n\n### Почему это проблема\n\nПаспортные данные, пароли, банковские реквизиты и секретные ключи не требуются для оформления обычной закупочной заявки и создают риск утечки.\n\n### Как исправить\n\nУдалите или обезличьте чувствительные сведения. Передавайте только данные, необходимые для описания потребности.\n\n**Плохо:**\n\n> В сообщении указаны пароль от системы, паспорт сотрудника и банковские реквизиты.\n\n**Хорошо:**\n\n> Указано название системы, требуемый объём услуги и контакт ответственного сотрудника без секретных данных.\n\n## 13. Не приложен необходимый документ\n\n### Почему это проблема\n\nДля сложной закупки одного краткого описания может быть недостаточно. Без технического задания, макета, перечня адресов или спецификации закупщик не сможет корректно запросить предложение.\n\n### Как исправить\n\nПриложите документ или укажите, кто и когда его предоставит. До появления функции загрузки файлов можно сохранить заявку как черновик.\n\n**Плохо:**\n\n> Нужно изготовить вывески для всех магазинов, подробности потом.\n\n**Хорошо:**\n\n> Нужно изготовить вывески для 12 магазинов. Перечень адресов, размеры и макеты подготовлены в отдельной спецификации и будут приложены к заявке.\n\n## 14. Не описана совместимость\n\n### Почему это проблема\n\nТовар может соответствовать общим характеристикам, но не работать с существующим оборудованием или программным обеспечением.\n\n### Как исправить\n\nУкажите модели оборудования, типы разъёмов, версии систем и другие обязательные условия совместимости.\n\n**Плохо:**\n\n> Нужен блок питания для ноутбука.\n\n**Хорошо:**\n\n> Нужен блок питания мощностью 65 Вт с USB-C Power Delivery, совместимый с ноутбуками Dell Latitude 5440.\n\n## 15. Не определён ожидаемый результат услуги\n\n### Почему это проблема\n\nПеречень действий исполнителя не всегда показывает, какой результат должен получить заказчик.\n\n### Как исправить\n\nСформулируйте итоговый результат, формат передачи и назначение.\n\n**Плохо:**\n\n> Провести анализ сайта.\n\n**Хорошо:**\n\n> Провести UX-аудит сайта и передать отчёт с перечнем проблем, приоритетами, скриншотами и рекомендациями по исправлению.\n\n## 16. Указана сумма по позиции, но не общая сумма\n\n### Почему это проблема\n\nМаршрут согласования определяется по общей стоимости заявки. Ошибка в расчёте может привести к неверному согласованию.\n\n### Как исправить\n\nПроверьте количество, цену за единицу и итоговую сумму.\n\n**Плохо:**\n\n> 10 мониторов по 22 000 рублей, общий бюджет не указан.\n\n**Хорошо:**\n\n> 10 мониторов по ориентировочной цене 22 000 рублей. Общий бюджет — 220 000 рублей.\n",
    "document_id": "kb-015",
    "document_type": "error_guide",
    "effective_date": "2026-07-23",
    "filename": "14_Типовые_ошибки_при_оформлении_заявок.md",
    "language": "ru",
    "owner": "Отдел закупок",
    "priority": 9,
    "raw_content": "---\ndocument_id: kb-015\ntitle: Типовые ошибки при оформлении заявок\ndocument_type: error_guide\nversion: \"1.0\"\neffective_date: \"2026-07-23\"\nowner: Отдел закупок\npriority: 9\nstatus: active\nlanguage: ru\n---\n\n# Типовые ошибки при оформлении заявок\n\n## 1. Слишком общее описание потребности\n\n### Почему это проблема\n\nФормулировки «нужно оборудование», «нужна реклама» или «заказать доставку» не позволяют определить предмет закупки, категорию и обязательные требования.\n\n### Как исправить\n\nУкажите, что именно требуется, для какой цели и какой результат ожидается.\n\n**Плохо:**\n\n> Нужно оборудование для офиса.\n\n**Хорошо:**\n\n> Нужно 5 ноутбуков для новых сотрудников отдела продаж. Они будут использоваться для офисных программ, видеоконференций и работы в CRM.\n\n## 2. Отсутствует количество или объём\n\n### Почему это проблема\n\nБез количества товара или объёма услуги невозможно оценить бюджет, сроки и способ закупки.\n\n### Как исправить\n\nУкажите числовое значение и единицу измерения. Для услуги опишите объём работ.\n\n**Плохо:**\n\n> Нужно заказать офисную бумагу.\n\n**Хорошо:**\n\n> Нужно заказать 100 пачек офисной бумаги формата A4 по 500 листов.\n\n## 3. Не указана единица измерения\n\n### Почему это проблема\n\nЧисло без единицы измерения может трактоваться по-разному: штуки, упаковки, комплекты, часы или месяцы.\n\n### Как исправить\n\nВсегда указывайте единицу измерения рядом с количеством.\n\n**Плохо:**\n\n> Требуется 20 кабелей.\n\n**Хорошо:**\n\n> Требуется 20 штук кабелей HDMI длиной 2 метра.\n\n## 4. Использованы субъективные требования\n\n### Почему это проблема\n\nФормулировки «качественный», «красивый», «современный» или «удобный» нельзя объективно проверить при выборе и приёмке.\n\n### Как исправить\n\nЗамените субъективные ожидания измеримыми характеристиками или критериями.\n\n**Плохо:**\n\n> Нужны красивые и удобные кресла.\n\n**Хорошо:**\n\n> Нужны офисные кресла с регулируемой высотой, поясничной поддержкой, подлокотниками и допустимой нагрузкой не менее 120 кг.\n\n## 5. Указана только ссылка на товар\n\n### Почему это проблема\n\nСтраница по ссылке может измениться или стать недоступной. Кроме того, ссылка не объясняет, какие характеристики действительно обязательны.\n\n### Как исправить\n\nИспользуйте ссылку как пример, но отдельно перечислите обязательные параметры.\n\n**Плохо:**\n\n> Купите вот это: https://example.com/product.\n\n**Хорошо:**\n\n> Ссылка приведена как референс. Обязательные характеристики: диагональ 24–27 дюймов, разрешение не ниже Full HD, HDMI, регулировка наклона.\n\n## 6. Указан конкретный бренд без обоснования\n\n### Почему это проблема\n\nНеобоснованное ограничение бренда сокращает конкуренцию и может увеличить стоимость или срок закупки.\n\n### Как исправить\n\nУкажите «или эквивалент». Если эквивалент недопустим, объясните объективную причину: совместимость, единый парк оборудования, требования гарантии или утверждённый стандарт.\n\n**Плохо:**\n\n> Нужны только мониторы Samsung.\n\n**Хорошо:**\n\n> Нужны мониторы Samsung или эквивалент с указанными характеристиками.\n\n**Хорошо при запрете эквивалента:**\n\n> Нужны терминалы конкретной модели, поскольку они должны работать с уже установленными док-станциями и корпоративным образом системы. Совместимость другой модели не подтверждена.\n\n## 7. Нет критериев приёмки услуги\n\n### Почему это проблема\n\nБез критериев приёмки невозможно однозначно определить, выполнена ли услуга и соответствует ли результат ожиданиям.\n\n### Как исправить\n\nОпишите конкретный результат и способ его проверки.\n\n**Плохо:**\n\n> Сделать качественную презентацию.\n\n**Хорошо:**\n\n> Подготовить презентацию на 15–20 слайдов в корпоративном шаблоне, передать редактируемый файл PPTX и PDF, устранить замечания после одного раунда согласования.\n\n## 8. Указана прошедшая или противоречивая дата\n\n### Почему это проблема\n\nПоставка не может быть запланирована на прошедшую дату, а окончание услуги не может быть раньше её начала.\n\n### Как исправить\n\nПроверьте календарные даты и учитывайте нормативный срок закупки.\n\n**Плохо:**\n\n> Подать заявку 20 июля, поставка нужна 15 июля.\n\n**Хорошо:**\n\n> Заявка подаётся 20 июля, требуемая дата поставки — 20 августа.\n\n## 9. Не указан бюджет или бюджетный статус\n\n### Почему это проблема\n\nБез ориентировочной суммы и понимания, предусмотрены ли расходы бюджетом, нельзя определить маршрут согласования и реалистичность потребности.\n\n### Как исправить\n\nУкажите точную сумму, диапазон или максимально допустимый бюджет, а также бюджетный статус.\n\n**Плохо:**\n\n> Стоимость пока неизвестна.\n\n**Хорошо:**\n\n> Ориентировочный бюджет — 180 000–220 000 рублей, закупка предусмотрена бюджетом отдела.\n\n## 10. Срочность не обоснована\n\n### Почему это проблема\n\nФраза «нужно срочно» не объясняет причину и не позволяет определить приоритет заявки.\n\n### Как исправить\n\nУкажите причину срочности, последствия задержки, дату возникновения потребности и наличие временной альтернативы.\n\n**Плохо:**\n\n> Нужно очень срочно, желательно завтра.\n\n**Хорошо:**\n\n> Поставка нужна до 5 августа, поскольку 6 августа открывается новая торговая точка. При задержке сотрудники не смогут начать работу. Временной альтернативы нет.\n\n## 11. В одной заявке объединены разные категории\n\n### Почему это проблема\n\nТовары и услуги разных категорий могут иметь разные требования, сроки, поставщиков и маршруты согласования.\n\n### Как исправить\n\nРазделите потребности на отдельные заявки по однородным категориям.\n\n**Плохо:**\n\n> В одной заявке нужны кресла, лицензии на программное обеспечение и курьерская доставка.\n\n**Хорошо:**\n\n> Создать три заявки: на офисные кресла, на программные лицензии и на курьерскую услугу.\n\nНесколько позиций можно объединить, если они относятся к одной категории и закупаются совместно.\n\n## 12. Переданы лишние чувствительные данные\n\n### Почему это проблема\n\nПаспортные данные, пароли, банковские реквизиты и секретные ключи не требуются для оформления обычной закупочной заявки и создают риск утечки.\n\n### Как исправить\n\nУдалите или обезличьте чувствительные сведения. Передавайте только данные, необходимые для описания потребности.\n\n**Плохо:**\n\n> В сообщении указаны пароль от системы, паспорт сотрудника и банковские реквизиты.\n\n**Хорошо:**\n\n> Указано название системы, требуемый объём услуги и контакт ответственного сотрудника без секретных данных.\n\n## 13. Не приложен необходимый документ\n\n### Почему это проблема\n\nДля сложной закупки одного краткого описания может быть недостаточно. Без технического задания, макета, перечня адресов или спецификации закупщик не сможет корректно запросить предложение.\n\n### Как исправить\n\nПриложите документ или укажите, кто и когда его предоставит. До появления функции загрузки файлов можно сохранить заявку как черновик.\n\n**Плохо:**\n\n> Нужно изготовить вывески для всех магазинов, подробности потом.\n\n**Хорошо:**\n\n> Нужно изготовить вывески для 12 магазинов. Перечень адресов, размеры и макеты подготовлены в отдельной спецификации и будут приложены к заявке.\n\n## 14. Не описана совместимость\n\n### Почему это проблема\n\nТовар может соответствовать общим характеристикам, но не работать с существующим оборудованием или программным обеспечением.\n\n### Как исправить\n\nУкажите модели оборудования, типы разъёмов, версии систем и другие обязательные условия совместимости.\n\n**Плохо:**\n\n> Нужен блок питания для ноутбука.\n\n**Хорошо:**\n\n> Нужен блок питания мощностью 65 Вт с USB-C Power Delivery, совместимый с ноутбуками Dell Latitude 5440.\n\n## 15. Не определён ожидаемый результат услуги\n\n### Почему это проблема\n\nПеречень действий исполнителя не всегда показывает, какой результат должен получить заказчик.\n\n### Как исправить\n\nСформулируйте итоговый результат, формат передачи и назначение.\n\n**Плохо:**\n\n> Провести анализ сайта.\n\n**Хорошо:**\n\n> Провести UX-аудит сайта и передать отчёт с перечнем проблем, приоритетами, скриншотами и рекомендациями по исправлению.\n\n## 16. Указана сумма по позиции, но не общая сумма\n\n### Почему это проблема\n\nМаршрут согласования определяется по общей стоимости заявки. Ошибка в расчёте может привести к неверному согласованию.\n\n### Как исправить\n\nПроверьте количество, цену за единицу и итоговую сумму.\n\n**Плохо:**\n\n> 10 мониторов по 22 000 рублей, общий бюджет не указан.\n\n**Хорошо:**\n\n> 10 мониторов по ориентировочной цене 22 000 рублей. Общий бюджет — 220 000 рублей.\n",
    "sha256": "7de8da6d297e2915405e20d950ed483e4711f9865a9099ba19dd882bfd610aca",
    "status": "active",
    "title": "Типовые ошибки при оформлении заявок",
    "version": "1.0"
  }
]
